wedding/___objectives/OSM/OSM.S.HTML
wedding/___objectives/objectives.S.HTML
wedding/__dictionary/wedding_1
wedding/__init__.py
wedding/__licenses/license.S.HTML
wedding/__licenses/licenses/gpl-3.0-standalone.html
wedding/__licenses/licenses/non-business.S.HTML
wedding/_essence/__init__.py
wedding/_essence/essence.S.HTML
wedding/_essence/merge/__init__.py
wedding/_essence/scan/__init__.py
wedding/_essence/seek/__init__.py
wedding/_ops/_clique/__init__.py
wedding/_ops/_clique/group/__init__.py
wedding/_status/DB/records.json
wedding/_status/monitors/status_1.py
wedding/_status/status.proc.py
wedding/adventures/_ops/clique.py
wedding/adventures/_ops/off.py
wedding/adventures/_ops/on.py
wedding/adventures/_ops/refresh.py
wedding/adventures/_ops/status.py
wedding/adventures/alerting/__init__.py
wedding/adventures/alerting/parse_exception.py
wedding/adventures/monetary/.gitignore
wedding/adventures/monetary/__init__.py
wedding/adventures/monetary/__saves/saves.S.HTML
wedding/adventures/monetary/_ops/_clique.py
wedding/adventures/monetary/_ops/off.py
wedding/adventures/monetary/_ops/on.py
wedding/adventures/monetary/_ops/saves/_clique.py
wedding/adventures/monetary/_ops/saves/dumps/dump.py
wedding/adventures/monetary/_ops/saves/dumps/restore.py
wedding/adventures/monetary/_ops/saves/exports/export.py
wedding/adventures/monetary/_ops/saves/exports/import.py
wedding/adventures/monetary/_ops/saves/memories.S.HTML
wedding/adventures/monetary/_ops/status.py
wedding/adventures/monetary/databases/mesmerizing/connect.py
wedding/adventures/monetary/databases/mesmerizing/places/insert.py
wedding/adventures/monetary/monetary.S.HTML
wedding/adventures/monetary/moves/URL/retrieve.py
wedding/adventures/sanique/_ops/off.py
wedding/adventures/sanique/_ops/on.py
wedding/adventures/sanique/_ops/refresh.py
wedding/adventures/sanique/_ops/status.py
wedding/adventures/sanique/_status/API_status_besties__food_USDA__nature_v2__FDC_ID_1.py
wedding/adventures/sanique/clique.py
wedding-1.0.1.dist-info/METADATA
wedding-1.0.1.dist-info/WHEEL
wedding-1.0.1.dist-info/entry_points.txt
wedding-1.0.1.dist-info/RECORD
