Metadata-Version: 2.1
Name: wedding
Version: 1.0.1
Summary: Drawings of the wedding and fields.
License: GPL 3.0 Standalone + non-business
Requires-Python: >=3.10,<4.0
Classifier: License :: Other/Proprietary License
Classifier: Programming Language :: Python :: 3
Classifier: Programming Language :: Python :: 3.10
Classifier: Programming Language :: Python :: 3.11
Classifier: Programming Language :: Python :: 3.12
Requires-Dist: biotech (>=1.1.10,<2.0.0)
Requires-Dist: click (>=8.1.7,<9.0.0)
Requires-Dist: docker (>=7.0.0,<8.0.0)
Requires-Dist: law_dictionary (>=1.0.12,<2.0.0)
Requires-Dist: pydash (>=8.0.0,<9.0.0)
Requires-Dist: pymongo (>=4.6.3,<5.0.0)
Requires-Dist: receptors (>=0.0.1,<0.0.2)
Requires-Dist: rich (>=13.7.1,<14.0.0)
Requires-Dist: sanic (>=23.12.1,<24.0.0)
Requires-Dist: sanic-ext (>=23.12.0,<24.0.0)
Requires-Dist: setuptools (>=69.5.1,<70.0.0)
Requires-Dist: ships (>=1.2.6,<2.0.0)
Requires-Dist: somatic (>=3.0.3,<4.0.0)
Project-URL: GitLab, https://gitlab.com/status600/treasures/wedding.1
